<?xml version="1.0" encoding="UTF-8" standalone="yes"?>
	<app version="1.3">
		<name>Mandelbrot for Wii</name>
		<coder>krupkat</coder>
		<version>1.3</version>
		<release_date>Mar 12, 2010</release_date>
		<short_description>Mandelbrot Generator</short_description>
		<long_description>This is a Mandelbrot set generator, you could have seen them on other platforms as well e.g. FractInt for PC.

A - zoom
B - reset
-,+ - change palette
1,2 - change number of iterations
DOWN - run cycling palette
HOME - back to HBC

v1.3 - cycling palette
v1.2 - major speedup thanks to Dashxdr
v1.1 - wiimote friendly</long_description>
	</app>
